{
	"__CODENAME" : "conquest_coop_hard_ea830f0f-e05e-44a7-bbf1-f80f4364579b",
	"__DISPLAYNAME" : "Hell",
	"__DESCRIPTION" : "##mode_conquest_preset_coophard_info",
	"__PRESET_GAMEMODE" : "conquest",
	"__PRESET_ORDER" : 6,
	"__ASSETVERSION": 1,
	"__PRESET_ISDEFAULT" : false,
	"__PLAYABLECONTEXT" : 2,
	
	"MP_MinTeams" : 1,
	"MP_MaxTeams" : 1,
	"MP_MinPlayersPerTeam" : 1,
	"MP_MaxPlayersPerTeam" : -1,
	"MP_AllowSharingTeam" : true,
	
	"MP_MinFactions" : 1,
	"MP_MaxFactions" : -1,
	"MP_MinPlayersPerFaction" : -1,
	"MP_MaxPlayersPerFaction" : -1,
	"MP_AllowSharingFaction" : true,
  "MP_RequiresCorruptrons" : true,
	
	"levelClockInterval" : 300,
	"maximumEnemyLevel" : 10,
	"baseCorruptronOffense" : 16,
	"baseCorruptronDefense" : 48,
	"offenseIncreasePerLevel" : 10,
	"defenseIncreasePerLevel" : 4,
	"playerAttackInterval" : 220,
	"firstWaveDurationBonus" : 0,
	"neutralAttackInterval" : 180,
	"randomCorruptronCapture" : true,
	
	"hasRaidMissions" : true,

	"startingWorkersCount" : 3,
	"startingKnightCount" : 0,
	"startingArcherCount" : 0,
	
	"canDigGround" : true,
	"playerRelations" : 2,
	
	"blueCrystalDeeplayer" : false,
	"orangeCrystalDeeplayer" : true,
	"ironDeeplayer" : true,
}
